cinecli/__init__.py
cinecli/api.py
cinecli/cli.py
cinecli/config.py
cinecli/magnets.py
cinecli/ui.py
cinecli-0.1.2.dist-info/licenses/LICENSE
cinecli-0.1.2.dist-info/METADATA
cinecli-0.1.2.dist-info/WHEEL
cinecli-0.1.2.dist-info/entry_points.txt
cinecli-0.1.2.dist-info/top_level.txt
cinecli-0.1.2.dist-info/RECORD
